model_alarm_to_slack/slack_sender.py
slackForBalab/__init__.py
slackForBalab/slack_sender.py
slackForBalab-0.0.0.5.dist-info/METADATA
slackForBalab-0.0.0.5.dist-info/WHEEL
slackForBalab-0.0.0.5.dist-info/top_level.txt
slackForBalab-0.0.0.5.dist-info/RECORD
