Metadata-Version: 2.1
Name: slackForBalab
Version: 0.0.0.5
Summary: Sends a Slack notification when the model finishes or an error occurs.
Home-page: 
Author: 
Author-email: hj.jeong0609@gmail.com
License: MIT
Classifier: Intended Audience :: Science/Research
Classifier: Development Status :: 3 - Alpha
Classifier: License :: OSI Approved :: MIT License
Classifier: Programming Language :: Python :: 3.6
Classifier: Topic :: Scientific/Engineering :: Artificial Intelligence
Requires-Python: >=3.6
Requires-Dist: requests
